{"assets":{"75DDB4FB0C8EE7EE82813E41EF6560A1":{"type":"texture","index":3,"assetRequest":{"type":"slide","state":"contents","slide":"none"},"url":{"native":"assets/516C9944-A2CC-4291-A078-EF6FC6B1A97D.pdf"},"width":750,"height":1334},"5BAF8D745688545466A570CB1046F95A":{"type":"texture","index":2,"assetRequest":{"type":"slide","state":"contents","slide":"none"},"url":{"native":"assets/516C9944-A2CC-4291-A078-EF6FC6B1A97D.pdf"},"width":750,"height":1334},"DDA4DFE51FE726C87FFA22F174C2FB64":{"type":"texture","index":1,"assetRequest":{"type":"slide","state":"contents","slide":"none"},"url":{"native":"assets/516C9944-A2CC-4291-A078-EF6FC6B1A97D.pdf"},"width":750,"height":1334},"97F06324BA3636EBCCC82A8C63D6F435":{"type":"texture","index":4,"assetRequest":{"type":"slide","state":"contents","slide":"none"},"url":{"native":"assets/516C9944-A2CC-4291-A078-EF6FC6B1A97D.pdf"},"width":750,"height":1334},"05444D77FABE9B6EB6A8CEE0A400DD09":{"type":"texture","index":0,"assetRequest":{"type":"slide","state":"contents","slide":"none"},"url":{"native":"assets/516C9944-A2CC-4291-A078-EF6FC6B1A97D.pdf"},"width":750,"height":1334}},"events":[{"effects":[{"beginTime":0,"baseLayer":{"animations":[],"initialState":{"affineTransform":[1,0,0,1,0,0],"masksToBounds":false,"rotation":0,"scale":1,"position":{"pointX":375,"pointY":667},"width":750,"sublayerTransform":[1,0,0,0,0,1,0,0,0,0,1,0,0,0,0,1],"contentsRect":{"y":0,"x":0,"width":1,"height":1},"opacity":1,"edgeAntialiasingMask":251658240,"height":1334,"hidden":false,"anchorPoint":{"pointX":0.5,"pointY":0.5}},"objectID":"0","layers":[{"animations":[],"initialState":{"affineTransform":[1,0,0,1,0,0],"masksToBounds":false,"rotation":0,"scale":1,"position":{"pointX":375,"pointY":667},"width":750,"sublayerTransform":[1,0,0,0,0,1,0,0,0,0,1,-0.0005041139395215742,0,0,0,1],"contentsRect":{"y":0,"x":0,"width":1,"height":1},"opacity":1,"edgeAntialiasingMask":251658240,"height":1334,"hidden":false,"anchorPoint":{"pointX":0.5,"pointY":0.5}},"layers":[{"animations":[],"layers":[],"texturedRectangle":{"isBackgroundTexture":false,"singleTextureOpacity":1,"textureType":0,"textBaseline":0,"textXHeight":0,"isVerticalText":false},"initialState":{"affineTransform":[1,0,0,1,0,0],"masksToBounds":false,"rotation":0,"scale":1,"position":{"pointX":375,"pointY":667},"width":750,"sublayerTransform":[1,0,0,0,0,1,0,0,0,0,1,0,0,0,0,1],"contentsRect":{"y":0,"x":0,"width":1,"height":1},"opacity":1,"edgeAntialiasingMask":0,"height":1334,"hidden":false,"anchorPoint":{"pointX":0.5,"pointY":0.5}},"texture":"DDA4DFE51FE726C87FFA22F174C2FB64"},{"animations":[{"timeOffset":0,"from":{"scalar":false},"beginTime":0,"repeatCount":0,"fillMode":"both","property":"hidden","autoreverses":false,"duration":0.01,"to":{"scalar":true}}],"layers":[],"texturedRectangle":{"isBackgroundTexture":false,"singleTextureOpacity":1,"textureType":0,"textBaseline":0,"textXHeight":0,"isVerticalText":false},"initialState":{"affineTransform":[1,0,0,1,0,0],"masksToBounds":false,"rotation":0,"scale":1,"position":{"pointX":375,"pointY":667},"width":750,"sublayerTransform":[1,0,0,0,0,1,0,0,0,0,1,0,0,0,0,1],"contentsRect":{"y":0,"x":0,"width":1,"height":1},"opacity":1,"edgeAntialiasingMask":0,"height":1334,"hidden":false,"anchorPoint":{"pointX":0.5,"pointY":0.5}},"texture":"05444D77FABE9B6EB6A8CEE0A400DD09"}]}]},"effects":[],"duration":0.01,"type":"transition","name":"none","objectID":"0"}],"automaticPlay":false,"hyperlinks":[{"url":"?slide=previous","events":{"471A62D9-611F-42D5-ABF2-8CD5BB03D5E4":{"effects":[{"beginTime":0,"baseLayer":{"animations":[],"initialState":{"affineTransform":[1,0,0,1,0,0],"masksToBounds":false,"rotation":0,"scale":1,"position":{"pointX":375,"pointY":667},"width":750,"sublayerTransform":[1,0,0,0,0,1,0,0,0,0,1,0,0,0,0,1],"contentsRect":{"y":0,"x":0,"width":1,"height":1},"opacity":1,"edgeAntialiasingMask":251658240,"height":1334,"hidden":false,"anchorPoint":{"pointX":0.5,"pointY":0.5}},"objectID":"0","layers":[{"animations":[],"initialState":{"affineTransform":[1,0,0,1,0,0],"masksToBounds":false,"rotation":0,"scale":1,"position":{"pointX":375,"pointY":667},"width":750,"sublayerTransform":[1,0,0,0,0,1,0,0,0,0,1,-0.0005041139395215742,0,0,0,1],"contentsRect":{"y":0,"x":0,"width":1,"height":1},"opacity":1,"edgeAntialiasingMask":251658240,"height":1334,"hidden":false,"anchorPoint":{"pointX":0.5,"pointY":0.5}},"layers":[{"animations":[],"layers":[],"texturedRectangle":{"isBackgroundTexture":false,"singleTextureOpacity":1,"textureType":0,"textBaseline":0,"textXHeight":0,"isVerticalText":false},"initialState":{"affineTransform":[1,0,0,1,0,0],"masksToBounds":false,"rotation":0,"scale":1,"position":{"pointX":375,"pointY":667},"width":750,"sublayerTransform":[1,0,0,0,0,1,0,0,0,0,1,0,0,0,0,1],"contentsRect":{"y":0,"x":0,"width":1,"height":1},"opacity":1,"edgeAntialiasingMask":0,"height":1334,"hidden":false,"anchorPoint":{"pointX":0.5,"pointY":0.5}},"texture":"5BAF8D745688545466A570CB1046F95A"},{"animations":[{"timeOffset":0,"from":{"scalar":false},"beginTime":0,"repeatCount":0,"fillMode":"both","property":"hidden","autoreverses":false,"duration":0.01,"to":{"scalar":true}}],"layers":[],"texturedRectangle":{"isBackgroundTexture":false,"singleTextureOpacity":1,"textureType":0,"textBaseline":0,"textXHeight":0,"isVerticalText":false},"initialState":{"affineTransform":[1,0,0,1,0,0],"masksToBounds":false,"rotation":0,"scale":1,"position":{"pointX":375,"pointY":667},"width":750,"sublayerTransform":[1,0,0,0,0,1,0,0,0,0,1,0,0,0,0,1],"contentsRect":{"y":0,"x":0,"width":1,"height":1},"opacity":1,"edgeAntialiasingMask":0,"height":1334,"hidden":false,"anchorPoint":{"pointX":0.5,"pointY":0.5}},"texture":"05444D77FABE9B6EB6A8CEE0A400DD09"}]}]},"effects":[],"duration":0.01,"type":"transition","name":"none","objectID":"0"}],"automaticPlay":false,"hyperlinks":[],"accessibility":[],"baseLayer":{"animations":[],"initialState":{"affineTransform":[1,0,0,1,0,0],"masksToBounds":false,"rotation":0,"scale":1,"position":{"pointX":375,"pointY":667},"width":750,"sublayerTransform":[1,0,0,0,0,1,0,0,0,0,1,0,0,0,0,1],"contentsRect":{"y":0,"x":0,"width":1,"height":1},"opacity":1,"edgeAntialiasingMask":251658240,"height":1334,"hidden":false,"anchorPoint":{"pointX":0.5,"pointY":0.5}},"objectID":"0","layers":[{"animations":[],"initialState":{"affineTransform":[1,0,0,1,0,0],"masksToBounds":false,"rotation":0,"scale":1,"position":{"pointX":375,"pointY":667},"width":750,"sublayerTransform":[1,0,0,0,0,1,0,0,0,0,1,-0.0005041139395215742,0,0,0,1],"contentsRect":{"y":0,"x":0,"width":1,"height":1},"opacity":1,"edgeAntialiasingMask":251658240,"height":1334,"hidden":false,"anchorPoint":{"pointX":0.5,"pointY":0.5}},"layers":[{"animations":[],"layers":[],"texturedRectangle":{"isBackgroundTexture":false,"singleTextureOpacity":1,"textureType":0,"textBaseline":0,"textXHeight":0,"isVerticalText":false},"initialState":{"affineTransform":[1,0,0,1,0,0],"masksToBounds":false,"rotation":0,"scale":1,"position":{"pointX":375,"pointY":667},"width":750,"sublayerTransform":[1,0,0,0,0,1,0,0,0,0,1,0,0,0,0,1],"contentsRect":{"y":0,"x":0,"width":1,"height":1},"opacity":1,"edgeAntialiasingMask":0,"height":1334,"hidden":false,"anchorPoint":{"pointX":0.5,"pointY":0.5}},"texture":"05444D77FABE9B6EB6A8CEE0A400DD09"}]}]}}},"targetRectangle":{"y":62.36224128362722,"x":646.8511886623317,"width":42.60895715597076,"height":24.79567307813654}},{"url":"?slideid=BFA27966-8C9C-4A47-8493-EF5EE9DE5471","events":{"BFA27966-8C9C-4A47-8493-EF5EE9DE5471":{"effects":[{"beginTime":0,"baseLayer":{"animations":[],"initialState":{"affineTransform":[1,0,0,1,0,0],"masksToBounds":false,"rotation":0,"scale":1,"position":{"pointX":375,"pointY":667},"width":750,"sublayerTransform":[1,0,0,0,0,1,0,0,0,0,1,0,0,0,0,1],"contentsRect":{"y":0,"x":0,"width":1,"height":1},"opacity":1,"edgeAntialiasingMask":251658240,"height":1334,"hidden":false,"anchorPoint":{"pointX":0.5,"pointY":0.5}},"objectID":"0","layers":[{"animations":[],"initialState":{"affineTransform":[1,0,0,1,0,0],"masksToBounds":false,"rotation":0,"scale":1,"position":{"pointX":375,"pointY":667},"width":750,"sublayerTransform":[1,0,0,0,0,1,0,0,0,0,1,-0.0005041139395215742,0,0,0,1],"contentsRect":{"y":0,"x":0,"width":1,"height":1},"opacity":1,"edgeAntialiasingMask":251658240,"height":1334,"hidden":false,"anchorPoint":{"pointX":0.5,"pointY":0.5}},"layers":[{"animations":[],"layers":[],"texturedRectangle":{"isBackgroundTexture":false,"singleTextureOpacity":1,"textureType":0,"textBaseline":0,"textXHeight":0,"isVerticalText":false},"initialState":{"affineTransform":[1,0,0,1,0,0],"masksToBounds":false,"rotation":0,"scale":1,"position":{"pointX":375,"pointY":667},"width":750,"sublayerTransform":[1,0,0,0,0,1,0,0,0,0,1,0,0,0,0,1],"contentsRect":{"y":0,"x":0,"width":1,"height":1},"opacity":1,"edgeAntialiasingMask":0,"height":1334,"hidden":false,"anchorPoint":{"pointX":0.5,"pointY":0.5}},"texture":"75DDB4FB0C8EE7EE82813E41EF6560A1"},{"animations":[{"timeOffset":0,"from":{"scalar":false},"beginTime":0,"repeatCount":0,"fillMode":"both","property":"hidden","autoreverses":false,"duration":0.01,"to":{"scalar":true}}],"layers":[],"texturedRectangle":{"isBackgroundTexture":false,"singleTextureOpacity":1,"textureType":0,"textBaseline":0,"textXHeight":0,"isVerticalText":false},"initialState":{"affineTransform":[1,0,0,1,0,0],"masksToBounds":false,"rotation":0,"scale":1,"position":{"pointX":375,"pointY":667},"width":750,"sublayerTransform":[1,0,0,0,0,1,0,0,0,0,1,0,0,0,0,1],"contentsRect":{"y":0,"x":0,"width":1,"height":1},"opacity":1,"edgeAntialiasingMask":0,"height":1334,"hidden":false,"anchorPoint":{"pointX":0.5,"pointY":0.5}},"texture":"05444D77FABE9B6EB6A8CEE0A400DD09"}]}]},"effects":[],"duration":0.01,"type":"transition","name":"none","objectID":"0"}],"automaticPlay":false,"hyperlinks":[],"accessibility":[],"baseLayer":{"animations":[],"initialState":{"affineTransform":[1,0,0,1,0,0],"masksToBounds":false,"rotation":0,"scale":1,"position":{"pointX":375,"pointY":667},"width":750,"sublayerTransform":[1,0,0,0,0,1,0,0,0,0,1,0,0,0,0,1],"contentsRect":{"y":0,"x":0,"width":1,"height":1},"opacity":1,"edgeAntialiasingMask":251658240,"height":1334,"hidden":false,"anchorPoint":{"pointX":0.5,"pointY":0.5}},"objectID":"0","layers":[{"animations":[],"initialState":{"affineTransform":[1,0,0,1,0,0],"masksToBounds":false,"rotation":0,"scale":1,"position":{"pointX":375,"pointY":667},"width":750,"sublayerTransform":[1,0,0,0,0,1,0,0,0,0,1,-0.0005041139395215742,0,0,0,1],"contentsRect":{"y":0,"x":0,"width":1,"height":1},"opacity":1,"edgeAntialiasingMask":251658240,"height":1334,"hidden":false,"anchorPoint":{"pointX":0.5,"pointY":0.5}},"layers":[{"animations":[{"timeOffset":0,"from":{"scalar":false},"beginTime":0,"repeatCount":0,"fillMode":"both","property":"hidden","autoreverses":false,"duration":0.01,"to":{"scalar":true}}],"layers":[],"texturedRectangle":{"isBackgroundTexture":false,"singleTextureOpacity":1,"textureType":0,"textBaseline":0,"textXHeight":0,"isVerticalText":false},"initialState":{"affineTransform":[1,0,0,1,0,0],"masksToBounds":false,"rotation":0,"scale":1,"position":{"pointX":375,"pointY":667},"width":750,"sublayerTransform":[1,0,0,0,0,1,0,0,0,0,1,0,0,0,0,1],"contentsRect":{"y":0,"x":0,"width":1,"height":1},"opacity":1,"edgeAntialiasingMask":0,"height":1334,"hidden":false,"anchorPoint":{"pointX":0.5,"pointY":0.5}},"texture":"05444D77FABE9B6EB6A8CEE0A400DD09"}]}]}}},"targetRectangle":{"y":1262.104370117188,"x":336.09814453125,"width":77.8037109375,"height":73.70458984375}},{"url":"?slideid=471A62D9-611F-42D5-ABF2-8CD5BB03D5E4","events":{"471A62D9-611F-42D5-ABF2-8CD5BB03D5E4":{"effects":[{"beginTime":0,"baseLayer":{"animations":[],"initialState":{"affineTransform":[1,0,0,1,0,0],"masksToBounds":false,"rotation":0,"scale":1,"position":{"pointX":375,"pointY":667},"width":750,"sublayerTransform":[1,0,0,0,0,1,0,0,0,0,1,0,0,0,0,1],"contentsRect":{"y":0,"x":0,"width":1,"height":1},"opacity":1,"edgeAntialiasingMask":251658240,"height":1334,"hidden":false,"anchorPoint":{"pointX":0.5,"pointY":0.5}},"objectID":"0","layers":[{"animations":[],"initialState":{"affineTransform":[1,0,0,1,0,0],"masksToBounds":false,"rotation":0,"scale":1,"position":{"pointX":375,"pointY":667},"width":750,"sublayerTransform":[1,0,0,0,0,1,0,0,0,0,1,-0.0005041139395215742,0,0,0,1],"contentsRect":{"y":0,"x":0,"width":1,"height":1},"opacity":1,"edgeAntialiasingMask":251658240,"height":1334,"hidden":false,"anchorPoint":{"pointX":0.5,"pointY":0.5}},"layers":[{"animations":[],"layers":[],"texturedRectangle":{"isBackgroundTexture":false,"singleTextureOpacity":1,"textureType":0,"textBaseline":0,"textXHeight":0,"isVerticalText":false},"initialState":{"affineTransform":[1,0,0,1,0,0],"masksToBounds":false,"rotation":0,"scale":1,"position":{"pointX":375,"pointY":667},"width":750,"sublayerTransform":[1,0,0,0,0,1,0,0,0,0,1,0,0,0,0,1],"contentsRect":{"y":0,"x":0,"width":1,"height":1},"opacity":1,"edgeAntialiasingMask":0,"height":1334,"hidden":false,"anchorPoint":{"pointX":0.5,"pointY":0.5}},"texture":"5BAF8D745688545466A570CB1046F95A"},{"animations":[{"timeOffset":0,"from":{"scalar":false},"beginTime":0,"repeatCount":0,"fillMode":"both","property":"hidden","autoreverses":false,"duration":0.01,"to":{"scalar":true}}],"layers":[],"texturedRectangle":{"isBackgroundTexture":false,"singleTextureOpacity":1,"textureType":0,"textBaseline":0,"textXHeight":0,"isVerticalText":false},"initialState":{"affineTransform":[1,0,0,1,0,0],"masksToBounds":false,"rotation":0,"scale":1,"position":{"pointX":375,"pointY":667},"width":750,"sublayerTransform":[1,0,0,0,0,1,0,0,0,0,1,0,0,0,0,1],"contentsRect":{"y":0,"x":0,"width":1,"height":1},"opacity":1,"edgeAntialiasingMask":0,"height":1334,"hidden":false,"anchorPoint":{"pointX":0.5,"pointY":0.5}},"texture":"05444D77FABE9B6EB6A8CEE0A400DD09"}]}]},"effects":[],"duration":0.01,"type":"transition","name":"none","objectID":"0"}],"automaticPlay":false,"hyperlinks":[],"accessibility":[],"baseLayer":{"animations":[],"initialState":{"affineTransform":[1,0,0,1,0,0],"masksToBounds":false,"rotation":0,"scale":1,"position":{"pointX":375,"pointY":667},"width":750,"sublayerTransform":[1,0,0,0,0,1,0,0,0,0,1,0,0,0,0,1],"contentsRect":{"y":0,"x":0,"width":1,"height":1},"opacity":1,"edgeAntialiasingMask":251658240,"height":1334,"hidden":false,"anchorPoint":{"pointX":0.5,"pointY":0.5}},"objectID":"0","layers":[{"animations":[],"initialState":{"affineTransform":[1,0,0,1,0,0],"masksToBounds":false,"rotation":0,"scale":1,"position":{"pointX":375,"pointY":667},"width":750,"sublayerTransform":[1,0,0,0,0,1,0,0,0,0,1,-0.0005041139395215742,0,0,0,1],"contentsRect":{"y":0,"x":0,"width":1,"height":1},"opacity":1,"edgeAntialiasingMask":251658240,"height":1334,"hidden":false,"anchorPoint":{"pointX":0.5,"pointY":0.5}},"layers":[{"animations":[{"timeOffset":0,"from":{"scalar":false},"beginTime":0,"repeatCount":0,"fillMode":"both","property":"hidden","autoreverses":false,"duration":0.01,"to":{"scalar":true}}],"layers":[],"texturedRectangle":{"isBackgroundTexture":false,"singleTextureOpacity":1,"textureType":0,"textBaseline":0,"textXHeight":0,"isVerticalText":false},"initialState":{"affineTransform":[1,0,0,1,0,0],"masksToBounds":false,"rotation":0,"scale":1,"position":{"pointX":375,"pointY":667},"width":750,"sublayerTransform":[1,0,0,0,0,1,0,0,0,0,1,0,0,0,0,1],"contentsRect":{"y":0,"x":0,"width":1,"height":1},"opacity":1,"edgeAntialiasingMask":0,"height":1334,"hidden":false,"anchorPoint":{"pointX":0.5,"pointY":0.5}},"texture":"05444D77FABE9B6EB6A8CEE0A400DD09"}]}]}}},"targetRectangle":{"y":54.10204553937082,"x":15.88437690284335,"width":25.85633327046644,"height":43.31606386158374}},{"url":"?slide=next","events":{"043F84F2-3D94-4FC1-BB03-414B49A6D609":{"effects":[{"beginTime":0,"baseLayer":{"animations":[],"initialState":{"affineTransform":[1,0,0,1,0,0],"masksToBounds":false,"rotation":0,"scale":1,"position":{"pointX":375,"pointY":667},"width":750,"sublayerTransform":[1,0,0,0,0,1,0,0,0,0,1,0,0,0,0,1],"contentsRect":{"y":0,"x":0,"width":1,"height":1},"opacity":1,"edgeAntialiasingMask":251658240,"height":1334,"hidden":false,"anchorPoint":{"pointX":0.5,"pointY":0.5}},"objectID":"0","layers":[{"animations":[],"initialState":{"affineTransform":[1,0,0,1,0,0],"masksToBounds":false,"rotation":0,"scale":1,"position":{"pointX":375,"pointY":667},"width":750,"sublayerTransform":[1,0,0,0,0,1,0,0,0,0,1,-0.0005041139395215742,0,0,0,1],"contentsRect":{"y":0,"x":0,"width":1,"height":1},"opacity":1,"edgeAntialiasingMask":251658240,"height":1334,"hidden":false,"anchorPoint":{"pointX":0.5,"pointY":0.5}},"layers":[{"animations":[],"layers":[],"texturedRectangle":{"isBackgroundTexture":false,"singleTextureOpacity":1,"textureType":0,"textBaseline":0,"textXHeight":0,"isVerticalText":false},"initialState":{"affineTransform":[1,0,0,1,0,0],"masksToBounds":false,"rotation":0,"scale":1,"position":{"pointX":375,"pointY":667},"width":750,"sublayerTransform":[1,0,0,0,0,1,0,0,0,0,1,0,0,0,0,1],"contentsRect":{"y":0,"x":0,"width":1,"height":1},"opacity":1,"edgeAntialiasingMask":0,"height":1334,"hidden":false,"anchorPoint":{"pointX":0.5,"pointY":0.5}},"texture":"DDA4DFE51FE726C87FFA22F174C2FB64"},{"animations":[{"timeOffset":0,"from":{"scalar":false},"beginTime":0,"repeatCount":0,"fillMode":"both","property":"hidden","autoreverses":false,"duration":0.01,"to":{"scalar":true}}],"layers":[],"texturedRectangle":{"isBackgroundTexture":false,"singleTextureOpacity":1,"textureType":0,"textBaseline":0,"textXHeight":0,"isVerticalText":false},"initialState":{"affineTransform":[1,0,0,1,0,0],"masksToBounds":false,"rotation":0,"scale":1,"position":{"pointX":375,"pointY":667},"width":750,"sublayerTransform":[1,0,0,0,0,1,0,0,0,0,1,0,0,0,0,1],"contentsRect":{"y":0,"x":0,"width":1,"height":1},"opacity":1,"edgeAntialiasingMask":0,"height":1334,"hidden":false,"anchorPoint":{"pointX":0.5,"pointY":0.5}},"texture":"05444D77FABE9B6EB6A8CEE0A400DD09"}]}]},"effects":[],"duration":0.01,"type":"transition","name":"none","objectID":"0"}],"automaticPlay":false,"hyperlinks":[],"accessibility":[],"baseLayer":{"animations":[],"initialState":{"affineTransform":[1,0,0,1,0,0],"masksToBounds":false,"rotation":0,"scale":1,"position":{"pointX":375,"pointY":667},"width":750,"sublayerTransform":[1,0,0,0,0,1,0,0,0,0,1,0,0,0,0,1],"contentsRect":{"y":0,"x":0,"width":1,"height":1},"opacity":1,"edgeAntialiasingMask":251658240,"height":1334,"hidden":false,"anchorPoint":{"pointX":0.5,"pointY":0.5}},"objectID":"0","layers":[{"animations":[],"initialState":{"affineTransform":[1,0,0,1,0,0],"masksToBounds":false,"rotation":0,"scale":1,"position":{"pointX":375,"pointY":667},"width":750,"sublayerTransform":[1,0,0,0,0,1,0,0,0,0,1,-0.0005041139395215742,0,0,0,1],"contentsRect":{"y":0,"x":0,"width":1,"height":1},"opacity":1,"edgeAntialiasingMask":251658240,"height":1334,"hidden":false,"anchorPoint":{"pointX":0.5,"pointY":0.5}},"layers":[{"animations":[{"timeOffset":0,"from":{"scalar":false},"beginTime":0,"repeatCount":0,"fillMode":"both","property":"hidden","autoreverses":false,"duration":0.01,"to":{"scalar":true}}],"layers":[],"texturedRectangle":{"isBackgroundTexture":false,"singleTextureOpacity":1,"textureType":0,"textBaseline":0,"textXHeight":0,"isVerticalText":false},"initialState":{"affineTransform":[1,0,0,1,0,0],"masksToBounds":false,"rotation":0,"scale":1,"position":{"pointX":375,"pointY":667},"width":750,"sublayerTransform":[1,0,0,0,0,1,0,0,0,0,1,0,0,0,0,1],"contentsRect":{"y":0,"x":0,"width":1,"height":1},"opacity":1,"edgeAntialiasingMask":0,"height":1334,"hidden":false,"anchorPoint":{"pointX":0.5,"pointY":0.5}},"texture":"05444D77FABE9B6EB6A8CEE0A400DD09"}]}]}}},"targetRectangle":{"y":62.36224249858782,"x":693.8975753810817,"width":42.60895715597076,"height":24.79567307813653}},{"url":"?slideid=B9825B51-677B-479A-8670-54B01C4BB533","events":{"B9825B51-677B-479A-8670-54B01C4BB533":{"effects":[{"beginTime":0,"baseLayer":{"animations":[],"initialState":{"affineTransform":[1,0,0,1,0,0],"masksToBounds":false,"rotation":0,"scale":1,"position":{"pointX":375,"pointY":667},"width":750,"sublayerTransform":[1,0,0,0,0,1,0,0,0,0,1,0,0,0,0,1],"contentsRect":{"y":0,"x":0,"width":1,"height":1},"opacity":1,"edgeAntialiasingMask":251658240,"height":1334,"hidden":false,"anchorPoint":{"pointX":0.5,"pointY":0.5}},"objectID":"0","layers":[{"animations":[],"initialState":{"affineTransform":[1,0,0,1,0,0],"masksToBounds":false,"rotation":0,"scale":1,"position":{"pointX":375,"pointY":667},"width":750,"sublayerTransform":[1,0,0,0,0,1,0,0,0,0,1,-0.0005041139395215742,0,0,0,1],"contentsRect":{"y":0,"x":0,"width":1,"height":1},"opacity":1,"edgeAntialiasingMask":251658240,"height":1334,"hidden":false,"anchorPoint":{"pointX":0.5,"pointY":0.5}},"layers":[{"animations":[],"layers":[],"texturedRectangle":{"isBackgroundTexture":false,"singleTextureOpacity":1,"textureType":0,"textBaseline":0,"textXHeight":0,"isVerticalText":false},"initialState":{"affineTransform":[1,0,0,1,0,0],"masksToBounds":false,"rotation":0,"scale":1,"position":{"pointX":375,"pointY":667},"width":750,"sublayerTransform":[1,0,0,0,0,1,0,0,0,0,1,0,0,0,0,1],"contentsRect":{"y":0,"x":0,"width":1,"height":1},"opacity":1,"edgeAntialiasingMask":0,"height":1334,"hidden":false,"anchorPoint":{"pointX":0.5,"pointY":0.5}},"texture":"97F06324BA3636EBCCC82A8C63D6F435"},{"animations":[{"timeOffset":0,"from":{"scalar":false},"beginTime":0,"repeatCount":0,"fillMode":"both","property":"hidden","autoreverses":false,"duration":0.01,"to":{"scalar":true}}],"layers":[],"texturedRectangle":{"isBackgroundTexture":false,"singleTextureOpacity":1,"textureType":0,"textBaseline":0,"textXHeight":0,"isVerticalText":false},"initialState":{"affineTransform":[1,0,0,1,0,0],"masksToBounds":false,"rotation":0,"scale":1,"position":{"pointX":375,"pointY":667},"width":750,"sublayerTransform":[1,0,0,0,0,1,0,0,0,0,1,0,0,0,0,1],"contentsRect":{"y":0,"x":0,"width":1,"height":1},"opacity":1,"edgeAntialiasingMask":0,"height":1334,"hidden":false,"anchorPoint":{"pointX":0.5,"pointY":0.5}},"texture":"05444D77FABE9B6EB6A8CEE0A400DD09"}]}]},"effects":[],"duration":0.01,"type":"transition","name":"none","objectID":"0"}],"automaticPlay":false,"hyperlinks":[],"accessibility":[],"baseLayer":{"animations":[],"initialState":{"affineTransform":[1,0,0,1,0,0],"masksToBounds":false,"rotation":0,"scale":1,"position":{"pointX":375,"pointY":667},"width":750,"sublayerTransform":[1,0,0,0,0,1,0,0,0,0,1,0,0,0,0,1],"contentsRect":{"y":0,"x":0,"width":1,"height":1},"opacity":1,"edgeAntialiasingMask":251658240,"height":1334,"hidden":false,"anchorPoint":{"pointX":0.5,"pointY":0.5}},"objectID":"0","layers":[{"animations":[],"initialState":{"affineTransform":[1,0,0,1,0,0],"masksToBounds":false,"rotation":0,"scale":1,"position":{"pointX":375,"pointY":667},"width":750,"sublayerTransform":[1,0,0,0,0,1,0,0,0,0,1,-0.0005041139395215742,0,0,0,1],"contentsRect":{"y":0,"x":0,"width":1,"height":1},"opacity":1,"edgeAntialiasingMask":251658240,"height":1334,"hidden":false,"anchorPoint":{"pointX":0.5,"pointY":0.5}},"layers":[{"animations":[{"timeOffset":0,"from":{"scalar":false},"beginTime":0,"repeatCount":0,"fillMode":"both","property":"hidden","autoreverses":false,"duration":0.01,"to":{"scalar":true}}],"layers":[],"texturedRectangle":{"isBackgroundTexture":false,"singleTextureOpacity":1,"textureType":0,"textBaseline":0,"textXHeight":0,"isVerticalText":false},"initialState":{"affineTransform":[1,0,0,1,0,0],"masksToBounds":false,"rotation":0,"scale":1,"position":{"pointX":375,"pointY":667},"width":750,"sublayerTransform":[1,0,0,0,0,1,0,0,0,0,1,0,0,0,0,1],"contentsRect":{"y":0,"x":0,"width":1,"height":1},"opacity":1,"edgeAntialiasingMask":0,"height":1334,"hidden":false,"anchorPoint":{"pointX":0.5,"pointY":0.5}},"texture":"05444D77FABE9B6EB6A8CEE0A400DD09"}]}]}}},"targetRectangle":{"y":1269.448852539062,"x":24.50667572021484,"width":75.4404296875,"height":66.360107421875}}],"accessibility":[{"text":"Médecins Sans Frontières","targetRectangle":{"y":58.1468425989151,"x":179.6557312011719,"width":424.2073170731705,"height":43}},{"text":"Donate","targetRectangle":{"y":1305.121460437775,"x":340.78564453125,"width":67.4287109375,"height":26}},{"text":"Project Descriptions","targetRectangle":{"y":645.4999985694885,"x":45.51164245605469,"width":366.6260162601625,"height":47}},{"text":"                 ","targetRectangle":{"y":2.597426235675812,"x":2.9296875,"width":179.588,"height":53.87728485573462}},{"text":"pasted-image.png","targetRectangle":{"y":139.8020172119141,"x":252.4261627197266,"width":200,"height":217}},{"text":"South Sudan","targetRectangle":{"y":838.052073597908,"x":441.4751139501246,"width":223.0243902439024,"height":43}},{"text":"MAY 2015","targetRectangle":{"y":872.452074110508,"x":500.5919838688237,"width":104.7906504065041,"height":26}},{"text":"pasted-image.png","targetRectangle":{"y":441.033203125,"x":277.9261474609375,"width":149,"height":171}},{"text":"South Africa.jpg","targetRectangle":{"y":709.7766723632812,"x":397.3340759277344,"width":309.21875,"height":323.4375}},{"text":"Niger Delta","targetRectangle":{"y":1187.734374642372,"x":454.0776262283325,"width":195.7317073170732,"height":43}},{"text":"pasted-image.png","targetRectangle":{"y":385.708251953125,"x":10.78200054168701,"width":213,"height":230}},{"text":"Nigeria.jpg","targetRectangle":{"y":709.7766723632812,"x":48.03261947631836,"width":309.21875,"height":323.4375}},{"text":"pasted-image.png","targetRectangle":{"y":142.2415313720703,"x":433.9779357910156,"width":296,"height":218}},{"text":"                 ","targetRectangle":{"y":36.59742623567581,"x":2.9296875,"width":179.588,"height":53.87728485573462}},{"text":"pasted-image.png","targetRectangle":{"y":408.533203125,"x":436.5949401855469,"width":317,"height":224}},{"text":"Tanzania","targetRectangle":{"y":1187.734374642372,"x":126.0871222019196,"width":153.109756097561,"height":43}},{"text":"100%","targetRectangle":{"y":4.862236857414246,"x":605.6330569040756,"width":75.91869918699183,"height":33}},{"text":"Niger Delta.jpg","targetRectangle":{"y":1076.211547851562,"x":397.3341064453125,"width":309.21875,"height":323.4375}},{"text":"My Account","targetRectangle":{"y":1305.121460437775,"x":622.9930419921875,"width":110.8916015625,"height":26}},{"text":"Search","targetRectangle":{"y":1305.121460437775,"x":29.19417572021484,"width":65.0654296875,"height":26}},{"text":"Nigeria","targetRectangle":{"y":838.052073597908,"x":140.3554131771491,"width":124.5731707317073,"height":43}},{"text":"AUGUST 2015","targetRectangle":{"y":872.452074110508,"x":127.8777709007263,"width":149.5284552845529,"height":26}},{"text":"pasted-image.png","targetRectangle":{"y":125.8468322753906,"x":16.28200149536133,"width":202,"height":227}},{"text":"Tanzania.jpg","targetRectangle":{"y":1076.211557388306,"x":48.03261947631836,"width":309.21875,"height":322.9390258789062}},{"text":"9:41 AM","targetRectangle":{"y":4.362235724925995,"x":328.549964819792,"width":100.829268292683,"height":30}},{"text":"                 ","targetRectangle":{"y":2.597426235675812,"x":2.9296875,"width":179.588,"height":53.87728485573462}}],"baseLayer":{"animations":[],"initialState":{"affineTransform":[1,0,0,1,0,0],"masksToBounds":false,"rotation":0,"scale":1,"position":{"pointX":375,"pointY":667},"width":750,"sublayerTransform":[1,0,0,0,0,1,0,0,0,0,1,0,0,0,0,1],"contentsRect":{"y":0,"x":0,"width":1,"height":1},"opacity":1,"edgeAntialiasingMask":251658240,"height":1334,"hidden":false,"anchorPoint":{"pointX":0.5,"pointY":0.5}},"objectID":"0","layers":[{"animations":[],"initialState":{"affineTransform":[1,0,0,1,0,0],"masksToBounds":false,"rotation":0,"scale":1,"position":{"pointX":375,"pointY":667},"width":750,"sublayerTransform":[1,0,0,0,0,1,0,0,0,0,1,-0.0005041139395215742,0,0,0,1],"contentsRect":{"y":0,"x":0,"width":1,"height":1},"opacity":1,"edgeAntialiasingMask":251658240,"height":1334,"hidden":false,"anchorPoint":{"pointX":0.5,"pointY":0.5}},"layers":[{"animations":[],"layers":[],"texturedRectangle":{"isBackgroundTexture":false,"singleTextureOpacity":1,"textureType":0,"textBaseline":0,"textXHeight":0,"isVerticalText":false},"initialState":{"affineTransform":[1,0,0,1,0,0],"masksToBounds":false,"rotation":0,"scale":1,"position":{"pointX":375,"pointY":667},"width":750,"sublayerTransform":[1,0,0,0,0,1,0,0,0,0,1,0,0,0,0,1],"contentsRect":{"y":0,"x":0,"width":1,"height":1},"opacity":1,"edgeAntialiasingMask":0,"height":1334,"hidden":false,"anchorPoint":{"pointX":0.5,"pointY":0.5}},"texture":"05444D77FABE9B6EB6A8CEE0A400DD09"}]}]}}]}